stx/__init__.py
stx/action.py
stx/app.py
stx/document.py
stx/logger.py
stx/compiling/__init__.py
stx/compiling/compiler.py
stx/compiling/composer.py
stx/compiling/marks.py
stx/compiling/linking/__init__.py
stx/compiling/linking/numbering.py
stx/compiling/linking/referencing.py
stx/compiling/parsing/__init__.py
stx/compiling/parsing/parser.py
stx/compiling/reading/__init__.py
stx/compiling/reading/chain.py
stx/compiling/reading/content.py
stx/compiling/reading/location.py
stx/compiling/reading/reader.py
stx/components/__init__.py
stx/components/_captured_text.py
stx/components/_code_block.py
stx/components/_component.py
stx/components/_composite.py
stx/components/_content_box.py
stx/components/_custom_text.py
stx/components/_figure.py
stx/components/_function_call.py
stx/components/_image.py
stx/components/_layout.py
stx/components/_link_text.py
stx/components/_list_block.py
stx/components/_literal.py
stx/components/_paragraph.py
stx/components/_plain_text.py
stx/components/_section.py
stx/components/_separator.py
stx/components/_styled_text.py
stx/components/_table.py
stx/components/_table_row.py
stx/components/_toc.py
stx/data_notation/__init__.py
stx/data_notation/parsing.py
stx/data_notation/values.py
stx/functions/__init__.py
stx/functions/core.py
stx/functions/registry.py
stx/functions/utils.py
stx/functions/built_in/__init__.py
stx/functions/built_in/_admonition.py
stx/functions/built_in/_code.py
stx/functions/built_in/_custom_style.py
stx/functions/built_in/_embed.py
stx/functions/built_in/_image.py
stx/functions/built_in/_layout.py
stx/functions/built_in/_line_feed.py
stx/functions/built_in/_toc.py
stx/grammars/__init__.py
stx/grammars/registry.py
stx/outputs/__init__.py
stx/outputs/output_action.py
stx/outputs/registry.py
stx/outputs/writer.py
stx/outputs/html/__init__.py
stx/outputs/html/dom.py
stx/outputs/html/escaping.py
stx/outputs/html/output.py
stx/outputs/html/serializer.py
stx/outputs/html/themes.py
stx/outputs/json/__init__.py
stx-0.1.11.dist-info/LICENSE
stx-0.1.11.dist-info/METADATA
stx-0.1.11.dist-info/WHEEL
stx-0.1.11.dist-info/entry_points.txt
stx-0.1.11.dist-info/top_level.txt
stx-0.1.11.dist-info/RECORD
